clean_menu/__init__.py
clean_menu/__main__.py
clean_menu-0.2.1.dist-info/LICENSE
clean_menu-0.2.1.dist-info/WHEEL
clean_menu-0.2.1.dist-info/METADATA
clean_menu-0.2.1.dist-info/RECORD
