Metadata-Version: 2.1
Name: clean-menu
Version: 0.2.1
Summary: Minimal library fot making menus within the console
Home-page: https://github.com/PetchouDev/cleanMenu
Author: PetchouDev
Author-email: petchou91d@gmail.com
Requires-Python: >=3.9,<4.0
Classifier: Programming Language :: Python :: 3
Classifier: Programming Language :: Python :: 3.9
Classifier: Programming Language :: Python :: 3.10
Classifier: Programming Language :: Python :: 3.11
Requires-Dist: art (>=5.7,<6.0)
Requires-Dist: colorama (>=0.4.6,<0.5.0)
Requires-Dist: pynput (>=1.7.6,<2.0.0)
Requires-Dist: termcolor (>=2.1.0,<3.0.0)
Project-URL: Repository, https://github.com/PetchouDev/cleanMenu
